src/__about__.py
src/ace_rtsw.py
solar_wind_archive-1.0.0.dist-info/METADATA
solar_wind_archive-1.0.0.dist-info/WHEEL
solar_wind_archive-1.0.0.dist-info/licenses/LICENSE
solar_wind_archive-1.0.0.dist-info/RECORD
