Metadata-Version: 2.3
Name: solar_wind_archive
Version: 1.0.0
Summary: A Python package that accesses current and historical ACE solar wind data.
Project-URL: Documentation, https://github.com/a-urq/solar_wind_archive#readme
Project-URL: Issues, https://github.com/a-urq/solar_wind_archive/issues
Project-URL: Source, https://github.com/a-urq/solar_wind_archive
Author-email: Amelia Urquhart <amelia.r.urquhart@gmail.com>
License-Expression: MIT
License-File: LICENSE
Classifier: Development Status :: 4 - Beta
Classifier: Programming Language :: Python
Classifier: Programming Language :: Python :: 3.8
Classifier: Programming Language :: Python :: 3.9
Classifier: Programming Language :: Python :: 3.10
Classifier: Programming Language :: Python :: 3.11
Classifier: Programming Language :: Python :: 3.12
Classifier: Programming Language :: Python :: Implementation :: CPython
Classifier: Programming Language :: Python :: Implementation :: PyPy
Requires-Python: >=3.8
